{
  "version": "1.0.0",
  "updateTime": "2026-04-14",
  "description": "豆瓣电影Top250与TMDB ID映射表",
  "source": "https://movie.douban.com/top250",
  "total": 250,
  "movies": [
    {
      "doubanRank": 1,
      "doubanId": "1292052",
      "tmdbId": 278,
      "imdbId": "",
      "title": "肖申克的救赎",
      "originalTitle": "The Shawshank Redemption",
      "year": "1994",
      "doubanRating": "9.7"
    },
    {
      "doubanRank": 2,
      "doubanId": "1291546",
      "tmdbId": 10997,
      "imdbId": "",
      "title": "霸王别姬",
      "originalTitle": "",
      "year": "1993",
      "doubanRating": "9.6"
    },
    {
      "doubanRank": 3,
      "doubanId": "1292722",
      "tmdbId": 597,
      "imdbId": "",
      "title": "泰坦尼克号",
      "originalTitle": "Titanic",
      "year": "1997",
      "doubanRating": "9.5"
    },
    {
      "doubanRank": 4,
      "doubanId": "1292720",
      "tmdbId": 13,
      "imdbId": "",
      "title": "阿甘正传",
      "originalTitle": "Forrest Gump",
      "year": "1994",
      "doubanRating": "9.5"
    },
    {
      "doubanRank": 5,
      "doubanId": "1291561",
      "tmdbId": 129,
      "imdbId": "",
      "title": "千与千寻",
      "originalTitle": "千と千尋の神隠し",
      "year": "2001",
      "doubanRating": "9.4"
    },
    {
      "doubanRank": 6,
      "doubanId": "1292063",
      "tmdbId": 637,
      "imdbId": "",
      "title": "美丽人生",
      "originalTitle": "La vita è bella",
      "year": "1997",
      "doubanRating": "9.5"
    },
    {
      "doubanRank": 7,
      "doubanId": "1889243",
      "tmdbId": 157336,
      "imdbId": "",
      "title": "星际穿越",
      "originalTitle": "Interstellar",
      "year": "2014",
      "doubanRating": "9.4"
    },
    {
      "doubanRank": 8,
      "doubanId": "1295644",
      "tmdbId": 101,
      "imdbId": "",
      "title": "这个杀手不太冷",
      "originalTitle": "Léon",
      "year": "1994",
      "doubanRating": "9.4"
    },
    {
      "doubanRank": 9,
      "doubanId": "3541415",
      "tmdbId": 27205,
      "imdbId": "",
      "title": "盗梦空间",
      "originalTitle": "Inception",
      "year": "2010",
      "doubanRating": "9.4"
    },
    {
      "doubanRank": 10,
      "doubanId": "1292064",
      "tmdbId": 37165,
      "imdbId": "",
      "title": "楚门的世界",
      "originalTitle": "The Truman Show",
      "year": "1998",
      "doubanRating": "9.4"
    },
    {
      "doubanRank": 11,
      "doubanId": "1295124",
      "tmdbId": 424,
      "imdbId": "",
      "title": "辛德勒的名单",
      "originalTitle": "Schindler's List",
      "year": "1993",
      "doubanRating": "9.5"
    },
    {
      "doubanRank": 12,
      "doubanId": "3011091",
      "tmdbId": 28178,
      "imdbId": "",
      "title": "忠犬八公的故事",
      "originalTitle": "Hachi: A Dog's Tale",
      "year": "2009",
      "doubanRating": "9.4"
    },
    {
      "doubanRank": 13,
      "doubanId": "1292001",
      "tmdbId": 10376,
      "imdbId": "",
      "title": "海上钢琴师",
      "originalTitle": "La leggenda del pianista sull'oceano",
      "year": "1998",
      "doubanRating": "9.3"
    },
    {
      "doubanRank": 14,
      "doubanId": "25662329",
      "tmdbId": 269149,
      "imdbId": "",
      "title": "疯狂动物城",
      "originalTitle": "Zootopia",
      "year": "2016",
      "doubanRating": "9.3"
    },
    {
      "doubanRank": 15,
      "doubanId": "3793023",
      "tmdbId": 20453,
      "imdbId": "",
      "title": "三傻大闹宝莱坞",
      "originalTitle": "3 Idiots",
      "year": "2009",
      "doubanRating": "9.2"
    },
    {
      "doubanRank": 16,
      "doubanId": "2131459",
      "tmdbId": 10681,
      "imdbId": "",
      "title": "机器人总动员",
      "originalTitle": "WALL·E",
      "year": "2008",
      "doubanRating": "9.3"
    },
    {
      "doubanRank": 17,
      "doubanId": "1291549",
      "tmdbId": 5528,
      "imdbId": "",
      "title": "放牛班的春天",
      "originalTitle": "Les choristes",
      "year": "2004",
      "doubanRating": "9.3"
    },
    {
      "doubanRank": 18,
      "doubanId": "1307914",
      "tmdbId": 10775,
      "imdbId": "",
      "title": "无间道",
      "originalTitle": "無間道",
      "year": "2002",
      "doubanRating": "9.3"
    },
    {
      "doubanRank": 19,
      "doubanId": "1296141",
      "tmdbId": 37257,
      "imdbId": "",
      "title": "控方证人",
      "originalTitle": "Witness for the Prosecution",
      "year": "1957",
      "doubanRating": "9.6"
    },
    {
      "doubanRank": 20,
      "doubanId": "20495023",
      "tmdbId": 354912,
      "imdbId": "",
      "title": "寻梦环游记",
      "originalTitle": "Coco",
      "year": "2017",
      "doubanRating": "9.1"
    },
    {
      "doubanRank": 21,
      "doubanId": "1292213",
      "tmdbId": 21835,
      "imdbId": "",
      "title": "大话西游之大圣娶亲",
      "originalTitle": "西遊記大結局之仙履奇緣",
      "year": "1995",
      "doubanRating": "9.2"
    },
    {
      "doubanRank": 22,
      "doubanId": "5912992",
      "tmdbId": 81481,
      "imdbId": "",
      "title": "熔炉",
      "originalTitle": "도가니",
      "year": "2011",
      "doubanRating": "9.3"
    },
    {
      "doubanRank": 23,
      "doubanId": "6786002",
      "tmdbId": 77338,
      "imdbId": "",
      "title": "触不可及",
      "originalTitle": "Intouchables",
      "year": "2011",
      "doubanRating": "9.3"
    },
    {
      "doubanRank": 24,
      "doubanId": "1291841",
      "tmdbId": 238,
      "imdbId": "",
      "title": "教父",
      "originalTitle": "The Godfather",
      "year": "1972",
      "doubanRating": "9.3"
    },
    {
      "doubanRank": 25,
      "doubanId": "1293172",
      "tmdbId": 746,
      "imdbId": "",
      "title": "末代皇帝",
      "originalTitle": "The Last Emperor",
      "year": "1987",
      "doubanRating": "9.3"
    },
    {
      "doubanRank": 26,
      "doubanId": "1295038",
      "tmdbId": 671,
      "imdbId": "",
      "title": "哈利·波特与魔法石",
      "originalTitle": "Harry Potter and the Sorcerer's Stone",
      "year": "2001",
      "doubanRating": "9.2"
    },
    {
      "doubanRank": 27,
      "doubanId": "1849031",
      "tmdbId": 1402,
      "imdbId": "",
      "title": "当幸福来敲门",
      "originalTitle": "The Pursuit of Happyness",
      "year": "2006",
      "doubanRating": "9.1"
    },
    {
      "doubanRank": 28,
      "doubanId": "1291560",
      "tmdbId": 8392,
      "imdbId": "",
      "title": "龙猫",
      "originalTitle": "となりのトトロ",
      "year": "1988",
      "doubanRating": "9.2"
    },
    {
      "doubanRank": 29,
      "doubanId": "1292365",
      "tmdbId": 31439,
      "imdbId": "",
      "title": "活着",
      "originalTitle": "",
      "year": "1994",
      "doubanRating": "9.3"
    },
    {
      "doubanRank": 30,
      "doubanId": "3319755",
      "tmdbId": 43949,
      "imdbId": "",
      "title": "怦然心动",
      "originalTitle": "Flipped",
      "year": "2010",
      "doubanRating": "9.1"
    },
    {
      "doubanRank": 31,
      "doubanId": "1851857",
      "tmdbId": 155,
      "imdbId": "",
      "title": "蝙蝠侠：黑暗骑士",
      "originalTitle": "The Dark Knight",
      "year": "2008",
      "doubanRating": "9.2"
    },
    {
      "doubanRank": 32,
      "doubanId": "1291552",
      "tmdbId": 122,
      "imdbId": "",
      "title": "指环王3：王者无敌",
      "originalTitle": "The Lord of the Rings: The Return of the King",
      "year": "2003",
      "doubanRating": "9.3"
    },
    {
      "doubanRank": 33,
      "doubanId": "26752088",
      "tmdbId": 532753,
      "imdbId": "",
      "title": "我不是药神",
      "originalTitle": "",
      "year": "2018",
      "doubanRating": "9.0"
    },
    {
      "doubanRank": 34,
      "doubanId": "1300267",
      "tmdbId": 770,
      "imdbId": "",
      "title": "乱世佳人",
      "originalTitle": "Gone with the Wind",
      "year": "1939",
      "doubanRating": "9.3"
    },
    {
      "doubanRank": 35,
      "doubanId": "2129039",
      "tmdbId": 14160,
      "imdbId": "",
      "title": "飞屋环游记",
      "originalTitle": "Up",
      "year": "2009",
      "doubanRating": "9.1"
    },
    {
      "doubanRank": 36,
      "doubanId": "3742360",
      "tmdbId": 51533,
      "imdbId": "",
      "title": "让子弹飞",
      "originalTitle": "",
      "year": "2010",
      "doubanRating": "9.0"
    },
    {
      "doubanRank": 37,
      "doubanId": "1308807",
      "tmdbId": 4935,
      "imdbId": "",
      "title": "哈尔的移动城堡",
      "originalTitle": "ハウルの動く城",
      "year": "2004",
      "doubanRating": "9.1"
    },
    {
      "doubanRank": 38,
      "doubanId": "1293182",
      "tmdbId": 389,
      "imdbId": "",
      "title": "十二怒汉",
      "originalTitle": "12 Angry Men",
      "year": "1957",
      "doubanRating": "9.4"
    },
    {
      "doubanRank": 39,
      "doubanId": "25958717",
      "tmdbId": 365045,
      "imdbId": "",
      "title": "海蒂和爷爷",
      "originalTitle": "Heidi",
      "year": "2015",
      "doubanRating": "9.3"
    },
    {
      "doubanRank": 40,
      "doubanId": "21937452",
      "tmdbId": 255709,
      "imdbId": "",
      "title": "素媛",
      "originalTitle": "소원",
      "year": "2013",
      "doubanRating": "9.3"
    },
    {
      "doubanRank": 41,
      "doubanId": "1305487",
      "tmdbId": 640,
      "imdbId": "",
      "title": "猫鼠游戏",
      "originalTitle": "Catch Me If You Can",
      "year": "2002",
      "doubanRating": "9.1"
    },
    {
      "doubanRank": 42,
      "doubanId": "1291583",
      "tmdbId": 10515,
      "imdbId": "",
      "title": "天空之城",
      "originalTitle": "天空の城ラピュタ",
      "year": "1986",
      "doubanRating": "9.2"
    },
    {
      "doubanRank": 43,
      "doubanId": "1291858",
      "tmdbId": 25838,
      "imdbId": "",
      "title": "鬼子来了",
      "originalTitle": "",
      "year": "2000",
      "doubanRating": "9.3"
    },
    {
      "doubanRank": 44,
      "doubanId": "26387939",
      "tmdbId": 360814,
      "imdbId": "",
      "title": "摔跤吧！爸爸",
      "originalTitle": "Dangal",
      "year": "2016",
      "doubanRating": "9.0"
    },
    {
      "doubanRank": 45,
      "doubanId": "1929463",
      "tmdbId": 87827,
      "imdbId": "",
      "title": "少年派的奇幻漂流",
      "originalTitle": "Life of Pi",
      "year": "2012",
      "doubanRating": "9.1"
    },
    {
      "doubanRank": 46,
      "doubanId": "1296736",
      "tmdbId": 423,
      "imdbId": "",
      "title": "钢琴家",
      "originalTitle": "The Pianist",
      "year": "2002",
      "doubanRating": "9.3"
    },
    {
      "doubanRank": 47,
      "doubanId": "1291572",
      "tmdbId": 121,
      "imdbId": "",
      "title": "指环王2：双塔奇兵",
      "originalTitle": "The Lord of the Rings: The Two Towers",
      "year": "2002",
      "doubanRating": "9.2"
    },
    {
      "doubanRank": 48,
      "doubanId": "1291548",
      "tmdbId": 207,
      "imdbId": "",
      "title": "死亡诗社",
      "originalTitle": "Dead Poets Society",
      "year": "1989",
      "doubanRating": "9.2"
    },
    {
      "doubanRank": 49,
      "doubanId": "1299398",
      "tmdbId": 13345,
      "imdbId": "",
      "title": "大话西游之月光宝盒",
      "originalTitle": "西遊記第壹佰零壹回之月光寶盒",
      "year": "1995",
      "doubanRating": "9.0"
    },
    {
      "doubanRank": 50,
      "doubanId": "27060077",
      "tmdbId": 490132,
      "imdbId": "",
      "title": "绿皮书",
      "originalTitle": "Green Book",
      "year": "2018",
      "doubanRating": "8.9"
    },
    {
      "doubanRank": 51,
      "doubanId": "30170448",
      "tmdbId": 517814,
      "imdbId": "",
      "title": "何以为家",
      "originalTitle": "كفرناحوم",
      "year": "2018",
      "doubanRating": "9.1"
    },
    {
      "doubanRank": 52,
      "doubanId": "1298624",
      "tmdbId": 9475,
      "imdbId": "",
      "title": "闻香识女人",
      "originalTitle": "Scent of a Woman",
      "year": "1992",
      "doubanRating": "9.1"
    },
    {
      "doubanRank": 53,
      "doubanId": "1418019",
      "tmdbId": 47759,
      "imdbId": "",
      "title": "大闹天宫",
      "originalTitle": "",
      "year": "1961(中国大陆)",
      "doubanRating": "9.4"
    },
    {
      "doubanRank": 54,
      "doubanId": "1291843",
      "tmdbId": 603,
      "imdbId": "",
      "title": "黑客帝国",
      "originalTitle": "The Matrix",
      "year": "1999",
      "doubanRating": "9.1"
    },
    {
      "doubanRank": 55,
      "doubanId": "1291571",
      "tmdbId": 120,
      "imdbId": "",
      "title": "指环王1：护戒使者",
      "originalTitle": "The Lord of the Rings: The Fellowship of the Ring",
      "year": "2001",
      "doubanRating": "9.1"
    },
    {
      "doubanRank": 56,
      "doubanId": "1293839",
      "tmdbId": 804,
      "imdbId": "",
      "title": "罗马假日",
      "originalTitle": "Roman Holiday",
      "year": "1953",
      "doubanRating": "9.1"
    },
    {
      "doubanRank": 57,
      "doubanId": "1299131",
      "tmdbId": 240,
      "imdbId": "",
      "title": "教父2",
      "originalTitle": "The Godfather: Part II",
      "year": "1974",
      "doubanRating": "9.3"
    },
    {
      "doubanRank": 58,
      "doubanId": "1301753",
      "tmdbId": 8587,
      "imdbId": "",
      "title": "狮子王",
      "originalTitle": "The Lion King",
      "year": "1994",
      "doubanRating": "9.1"
    },
    {
      "doubanRank": 59,
      "doubanId": "1291828",
      "tmdbId": 11216,
      "imdbId": "",
      "title": "天堂电影院",
      "originalTitle": "Nuovo Cinema Paradiso",
      "year": "1988",
      "doubanRating": "9.2"
    },
    {
      "doubanRank": 60,
      "doubanId": "1291818",
      "tmdbId": 10451,
      "imdbId": "",
      "title": "饮食男女",
      "originalTitle": "飲食男女",
      "year": "1994",
      "doubanRating": "9.2"
    },
    {
      "doubanRank": 61,
      "doubanId": "21937445",
      "tmdbId": 242452,
      "imdbId": "",
      "title": "辩护人",
      "originalTitle": "변호인",
      "year": "2013",
      "doubanRating": "9.2"
    },
    {
      "doubanRank": 62,
      "doubanId": "1485260",
      "tmdbId": 4922,
      "imdbId": "",
      "title": "本杰明·巴顿奇事",
      "originalTitle": "The Curious Case of Benjamin Button",
      "year": "2008",
      "doubanRating": "9.0"
    },
    {
      "doubanRank": 63,
      "doubanId": "1292000",
      "tmdbId": 550,
      "imdbId": "",
      "title": "搏击俱乐部",
      "originalTitle": "Fight Club",
      "year": "1999",
      "doubanRating": "9.0"
    },
    {
      "doubanRank": 64,
      "doubanId": "1306029",
      "tmdbId": 453,
      "imdbId": "",
      "title": "美丽心灵",
      "originalTitle": "A Beautiful Mind",
      "year": "2001",
      "doubanRating": "9.1"
    },
    {
      "doubanRank": 65,
      "doubanId": "3008247",
      "tmdbId": 14574,
      "imdbId": "",
      "title": "穿条纹睡衣的男孩",
      "originalTitle": "The Boy in the Striped Pajamas",
      "year": "2008",
      "doubanRating": "9.2"
    },
    {
      "doubanRank": 66,
      "doubanId": "3011235",
      "tmdbId": 12445,
      "imdbId": "",
      "title": "哈利·波特与死亡圣器(下)",
      "originalTitle": "Harry Potter and the Deathly Hallows: Part 2",
      "year": "2011",
      "doubanRating": "9.0"
    },
    {
      "doubanRank": 67,
      "doubanId": "1292220",
      "tmdbId": 47002,
      "imdbId": "",
      "title": "情书",
      "originalTitle": "Love Letter",
      "year": "1995",
      "doubanRating": "8.9"
    },
    {
      "doubanRank": 68,
      "doubanId": "1293350",
      "tmdbId": 100,
      "imdbId": "",
      "title": "两杆大烟枪",
      "originalTitle": "Lock, Stock and Two Smoking Barrels",
      "year": "1998",
      "doubanRating": "9.1"
    },
    {
      "doubanRank": 69,
      "doubanId": "1900841",
      "tmdbId": 582,
      "imdbId": "",
      "title": "窃听风暴",
      "originalTitle": "Das Leben der Anderen",
      "year": "2006",
      "doubanRating": "9.2"
    },
    {
      "doubanRank": 70,
      "doubanId": "1294408",
      "tmdbId": 15121,
      "imdbId": "",
      "title": "音乐之声",
      "originalTitle": "The Sound of Music",
      "year": "1965",
      "doubanRating": "9.1"
    },
    {
      "doubanRank": 71,
      "doubanId": "1291543",
      "tmdbId": 9470,
      "imdbId": "",
      "title": "功夫",
      "originalTitle": "",
      "year": "2004",
      "doubanRating": "8.9"
    },
    {
      "doubanRank": 72,
      "doubanId": "1291544",
      "tmdbId": 673,
      "imdbId": "",
      "title": "哈利·波特与阿兹卡班的囚徒",
      "originalTitle": "Harry Potter and the Prisoner of Azkaban",
      "year": "2004",
      "doubanRating": "9.0"
    },
    {
      "doubanRank": 73,
      "doubanId": "1292402",
      "tmdbId": 10867,
      "imdbId": "",
      "title": "西西里的美丽传说",
      "originalTitle": "Malèna",
      "year": "2000",
      "doubanRating": "8.9"
    },
    {
      "doubanRank": 74,
      "doubanId": "1652587",
      "tmdbId": 19995,
      "imdbId": "",
      "title": "阿凡达",
      "originalTitle": "Avatar",
      "year": "2009",
      "doubanRating": "8.8"
    },
    {
      "doubanRank": 75,
      "doubanId": "26580232",
      "tmdbId": 411088,
      "imdbId": "",
      "title": "看不见的客人",
      "originalTitle": "Contratiempo",
      "year": "2016",
      "doubanRating": "8.8"
    },
    {
      "doubanRank": 76,
      "doubanId": "1292849",
      "tmdbId": 857,
      "imdbId": "",
      "title": "拯救大兵瑞恩",
      "originalTitle": "Saving Private Ryan",
      "year": "1998",
      "doubanRating": "9.1"
    },
    {
      "doubanRank": 77,
      "doubanId": "1293544",
      "tmdbId": 274,
      "imdbId": "",
      "title": "沉默的羔羊",
      "originalTitle": "The Silence of the Lambs",
      "year": "1991",
      "doubanRating": "8.9"
    },
    {
      "doubanRank": 78,
      "doubanId": "1303021",
      "tmdbId": 21334,
      "imdbId": "",
      "title": "小鞋子",
      "originalTitle": "بچه های آسمان",
      "year": "1997",
      "doubanRating": "9.2"
    },
    {
      "doubanRank": 79,
      "doubanId": "11525673",
      "tmdbId": 120467,
      "imdbId": "",
      "title": "布达佩斯大饭店",
      "originalTitle": "The Grand Budapest Hotel",
      "year": "2014",
      "doubanRating": "8.9"
    },
    {
      "doubanRank": 80,
      "doubanId": "1292343",
      "tmdbId": 1954,
      "imdbId": "",
      "title": "蝴蝶效应",
      "originalTitle": "The Butterfly Effect",
      "year": "2004",
      "doubanRating": "8.9"
    },
    {
      "doubanRank": 81,
      "doubanId": "1292224",
      "tmdbId": 510,
      "imdbId": "",
      "title": "飞越疯人院",
      "originalTitle": "One Flew Over the Cuckoo's Nest",
      "year": "1975",
      "doubanRating": "9.1"
    },
    {
      "doubanRank": 82,
      "doubanId": "36445098",
      "tmdbId": 1026227,
      "imdbId": "",
      "title": "还有明天",
      "originalTitle": "C'è ancora domani",
      "year": "2023",
      "doubanRating": "9.3"
    },
    {
      "doubanRank": 83,
      "doubanId": "2334904",
      "tmdbId": 11324,
      "imdbId": "",
      "title": "禁闭岛",
      "originalTitle": "Shutter Island",
      "year": "2010",
      "doubanRating": "8.9"
    },
    {
      "doubanRank": 84,
      "doubanId": "1292656",
      "tmdbId": 489,
      "imdbId": "",
      "title": "心灵捕手",
      "originalTitle": "Good Will Hunting",
      "year": "1997",
      "doubanRating": "9.0"
    },
    {
      "doubanRank": 85,
      "doubanId": "1780330",
      "tmdbId": 1124,
      "imdbId": "",
      "title": "致命魔术",
      "originalTitle": "The Prestige",
      "year": "2006",
      "doubanRating": "8.9"
    },
    {
      "doubanRank": 86,
      "doubanId": "1291832",
      "tmdbId": 680,
      "imdbId": "",
      "title": "低俗小说",
      "originalTitle": "Pulp Fiction",
      "year": "1994",
      "doubanRating": "8.9"
    },
    {
      "doubanRank": 87,
      "doubanId": "5322596",
      "tmdbId": 74308,
      "imdbId": "",
      "title": "超脱",
      "originalTitle": "Detachment",
      "year": "2011",
      "doubanRating": "9.0"
    },
    {
      "doubanRank": 88,
      "doubanId": "1296996",
      "tmdbId": 672,
      "imdbId": "",
      "title": "哈利·波特与密室",
      "originalTitle": "Harry Potter and the Chamber of Secrets",
      "year": "2002",
      "doubanRating": "8.9"
    },
    {
      "doubanRank": 89,
      "doubanId": "1292434",
      "tmdbId": 25538,
      "imdbId": "",
      "title": "一一",
      "originalTitle": "",
      "year": "2000",
      "doubanRating": "9.1"
    },
    {
      "doubanRank": 90,
      "doubanId": "1302425",
      "tmdbId": 53168,
      "imdbId": "",
      "title": "喜剧之王",
      "originalTitle": "喜劇之王",
      "year": "1999",
      "doubanRating": "8.8"
    },
    {
      "doubanRank": 91,
      "doubanId": "1300299",
      "tmdbId": 11423,
      "imdbId": "",
      "title": "杀人回忆",
      "originalTitle": "살인의 추억",
      "year": "2003",
      "doubanRating": "8.9"
    },
    {
      "doubanRank": 92,
      "doubanId": "1297192",
      "tmdbId": 2832,
      "imdbId": "",
      "title": "致命ID",
      "originalTitle": "Identity",
      "year": "2003",
      "doubanRating": "8.9"
    },
    {
      "doubanRank": 93,
      "doubanId": "1294371",
      "tmdbId": 3082,
      "imdbId": "",
      "title": "摩登时代",
      "originalTitle": "Modern Times",
      "year": "1936",
      "doubanRating": "9.3"
    },
    {
      "doubanRank": 94,
      "doubanId": "1292679",
      "tmdbId": 18329,
      "imdbId": "",
      "title": "春光乍泄",
      "originalTitle": "春光乍洩",
      "year": "1997",
      "doubanRating": "9.0"
    },
    {
      "doubanRank": 95,
      "doubanId": "1298070",
      "tmdbId": 22,
      "imdbId": "",
      "title": "加勒比海盗",
      "originalTitle": "Pirates of the Caribbean: The Curse of the Black Pearl",
      "year": "2003",
      "doubanRating": "8.8"
    },
    {
      "doubanRank": 96,
      "doubanId": "3442220",
      "tmdbId": 23128,
      "imdbId": "",
      "title": "海豚湾",
      "originalTitle": "The Cove",
      "year": "2009",
      "doubanRating": "9.3"
    },
    {
      "doubanRank": 97,
      "doubanId": "1292262",
      "tmdbId": 311,
      "imdbId": "",
      "title": "美国往事",
      "originalTitle": "Once Upon a Time in America",
      "year": "1984",
      "doubanRating": "9.1"
    },
    {
      "doubanRank": 98,
      "doubanId": "1865703",
      "tmdbId": 4977,
      "imdbId": "",
      "title": "红辣椒",
      "originalTitle": "パプリカ",
      "year": "2006",
      "doubanRating": "9.0"
    },
    {
      "doubanRank": 99,
      "doubanId": "1292223",
      "tmdbId": 807,
      "imdbId": "",
      "title": "七宗罪",
      "originalTitle": "Se7en",
      "year": "1995",
      "doubanRating": "8.8"
    },
    {
      "doubanRank": 100,
      "doubanId": "1306249",
      "tmdbId": 37703,
      "imdbId": "",
      "title": "唐伯虎点秋香",
      "originalTitle": "唐伯虎點秋香",
      "year": "1993",
      "doubanRating": "8.8"
    },
    {
      "doubanRank": 101,
      "doubanId": "6985810",
      "tmdbId": 103663,
      "imdbId": "",
      "title": "狩猎",
      "originalTitle": "Jagten",
      "year": "2012",
      "doubanRating": "9.1"
    },
    {
      "doubanRank": 102,
      "doubanId": "1297359",
      "tmdbId": 128,
      "imdbId": "",
      "title": "幽灵公主",
      "originalTitle": "もののけ姫",
      "year": "1997",
      "doubanRating": "8.9"
    },
    {
      "doubanRank": 103,
      "doubanId": "1305164",
      "tmdbId": 37185,
      "imdbId": "",
      "title": "甜蜜蜜",
      "originalTitle": "",
      "year": "1996",
      "doubanRating": "8.9"
    },
    {
      "doubanRank": 104,
      "doubanId": "27010768",
      "tmdbId": 496243,
      "imdbId": "",
      "title": "寄生虫",
      "originalTitle": "기생충",
      "year": "2019",
      "doubanRating": "8.8"
    },
    {
      "doubanRank": 105,
      "doubanId": "1428581",
      "tmdbId": 134575,
      "imdbId": "",
      "title": "天书奇谭",
      "originalTitle": "",
      "year": "1983(中国大陆)",
      "doubanRating": "9.2"
    },
    {
      "doubanRank": 106,
      "doubanId": "3395373",
      "tmdbId": 49026,
      "imdbId": "",
      "title": "蝙蝠侠：黑暗骑士崛起",
      "originalTitle": "The Dark Knight Rises",
      "year": "2012",
      "doubanRating": "8.9"
    },
    {
      "doubanRank": 107,
      "doubanId": "11026735",
      "tmdbId": 177572,
      "imdbId": "",
      "title": "超能陆战队",
      "originalTitle": "Big Hero 6",
      "year": "2014",
      "doubanRating": "8.8"
    },
    {
      "doubanRank": 108,
      "doubanId": "10777687",
      "tmdbId": 158445,
      "imdbId": "",
      "title": "7号房的礼物",
      "originalTitle": "7번방의 선물",
      "year": "2013",
      "doubanRating": "8.9"
    },
    {
      "doubanRank": 109,
      "doubanId": "1297630",
      "tmdbId": 745,
      "imdbId": "",
      "title": "第六感",
      "originalTitle": "The Sixth Sense",
      "year": "1999",
      "doubanRating": "8.9"
    },
    {
      "doubanRank": 110,
      "doubanId": "1461403",
      "tmdbId": 526431,
      "imdbId": "",
      "title": "茶馆",
      "originalTitle": "",
      "year": "1982(中国大陆)",
      "doubanRating": "9.5"
    },
    {
      "doubanRank": 111,
      "doubanId": "1296339",
      "tmdbId": 76,
      "imdbId": "",
      "title": "爱在黎明破晓前",
      "originalTitle": "Before Sunrise",
      "year": "1995",
      "doubanRating": "8.8"
    },
    {
      "doubanRank": 112,
      "doubanId": "1291990",
      "tmdbId": 80,
      "imdbId": "",
      "title": "爱在日落黄昏时",
      "originalTitle": "Before Sunset",
      "year": "2004",
      "doubanRating": "8.9"
    },
    {
      "doubanRank": 113,
      "doubanId": "1787291",
      "tmdbId": 31512,
      "imdbId": "",
      "title": "被嫌弃的松子的一生",
      "originalTitle": "嫌われ松子の一生",
      "year": "2006",
      "doubanRating": "8.8"
    },
    {
      "doubanRank": 114,
      "doubanId": "10533913",
      "tmdbId": 150540,
      "imdbId": "",
      "title": "头脑特工队",
      "originalTitle": "Inside Out",
      "year": "2015",
      "doubanRating": "8.8"
    },
    {
      "doubanRank": 115,
      "doubanId": "1309055",
      "tmdbId": 674,
      "imdbId": "",
      "title": "哈利·波特与火焰杯",
      "originalTitle": "Harry Potter and the Goblet of Fire",
      "year": "2005",
      "doubanRating": "8.8"
    },
    {
      "doubanRank": 116,
      "doubanId": "1395091",
      "tmdbId": 10494,
      "imdbId": "",
      "title": "未麻的部屋",
      "originalTitle": "Perfect Blue",
      "year": "1997",
      "doubanRating": "9.1"
    },
    {
      "doubanRank": 117,
      "doubanId": "1291999",
      "tmdbId": 11104,
      "imdbId": "",
      "title": "重庆森林",
      "originalTitle": "重慶森林",
      "year": "1994",
      "doubanRating": "8.8"
    },
    {
      "doubanRank": 118,
      "doubanId": "4202302",
      "tmdbId": 51739,
      "imdbId": "",
      "title": "借东西的小人阿莉埃蒂",
      "originalTitle": "借りぐらしのアリエッティ",
      "year": "2010",
      "doubanRating": "8.9"
    },
    {
      "doubanRank": 119,
      "doubanId": "1293359",
      "tmdbId": 4291,
      "imdbId": "",
      "title": "菊次郎的夏天",
      "originalTitle": "菊次郎の夏",
      "year": "1999",
      "doubanRating": "8.9"
    },
    {
      "doubanRank": 120,
      "doubanId": "2149806",
      "tmdbId": 16804,
      "imdbId": "",
      "title": "入殓师",
      "originalTitle": "おくりびと",
      "year": "2008",
      "doubanRating": "8.9"
    },
    {
      "doubanRank": 121,
      "doubanId": "1418834",
      "tmdbId": 142,
      "imdbId": "",
      "title": "断背山",
      "originalTitle": "Brokeback Mountain",
      "year": "2005",
      "doubanRating": "8.8"
    },
    {
      "doubanRank": 122,
      "doubanId": "1292370",
      "tmdbId": 162,
      "imdbId": "",
      "title": "剪刀手爱德华",
      "originalTitle": "Edward Scissorhands",
      "year": "1990",
      "doubanRating": "8.7"
    },
    {
      "doubanRank": 123,
      "doubanId": "1294639",
      "tmdbId": 197,
      "imdbId": "",
      "title": "勇敢的心",
      "originalTitle": "Braveheart",
      "year": "1995",
      "doubanRating": "8.9"
    },
    {
      "doubanRank": 124,
      "doubanId": "10577869",
      "tmdbId": 122906,
      "imdbId": "",
      "title": "时空恋旅人",
      "originalTitle": "About Time",
      "year": "2013",
      "doubanRating": "8.8"
    },
    {
      "doubanRank": 125,
      "doubanId": "2353023",
      "tmdbId": 10191,
      "imdbId": "",
      "title": "驯龙高手",
      "originalTitle": "How to Train Your Dragon",
      "year": "2010",
      "doubanRating": "8.8"
    },
    {
      "doubanRank": 126,
      "doubanId": "21318488",
      "tmdbId": 210577,
      "imdbId": "",
      "title": "消失的爱人",
      "originalTitle": "Gone Girl",
      "year": "2014",
      "doubanRating": "8.7"
    },
    {
      "doubanRank": 127,
      "doubanId": "1292337",
      "tmdbId": 2517,
      "imdbId": "",
      "title": "无人知晓",
      "originalTitle": "誰も知らない",
      "year": "2004",
      "doubanRating": "9.1"
    },
    {
      "doubanRank": 128,
      "doubanId": "1297447",
      "tmdbId": 30421,
      "imdbId": "",
      "title": "倩女幽魂",
      "originalTitle": "",
      "year": "1987",
      "doubanRating": "8.8"
    },
    {
      "doubanRank": 129,
      "doubanId": "1418200",
      "tmdbId": 4348,
      "imdbId": "",
      "title": "傲慢与偏见",
      "originalTitle": "Pride & Prejudice",
      "year": "2005",
      "doubanRating": "8.7"
    },
    {
      "doubanRank": 130,
      "doubanId": "10437779",
      "tmdbId": 165213,
      "imdbId": "",
      "title": "新世界",
      "originalTitle": "신세계",
      "year": "2013",
      "doubanRating": "8.9"
    },
    {
      "doubanRank": 131,
      "doubanId": "1291557",
      "tmdbId": 843,
      "imdbId": "",
      "title": "花样年华",
      "originalTitle": "花樣年華",
      "year": "2000",
      "doubanRating": "8.8"
    },
    {
      "doubanRank": 132,
      "doubanId": "1858711",
      "tmdbId": 10193,
      "imdbId": "",
      "title": "玩具总动员3",
      "originalTitle": "Toy Story 3",
      "year": "2010",
      "doubanRating": "8.9"
    },
    {
      "doubanRank": 133,
      "doubanId": "26628357",
      "tmdbId": 348678,
      "imdbId": "",
      "title": "一个叫欧维的男人决定去死",
      "originalTitle": "En man som heter Ove",
      "year": "2015",
      "doubanRating": "8.9"
    },
    {
      "doubanRank": 134,
      "doubanId": "1300992",
      "tmdbId": 9559,
      "imdbId": "",
      "title": "完美的世界",
      "originalTitle": "A Perfect World",
      "year": "1993",
      "doubanRating": "9.1"
    },
    {
      "doubanRank": 135,
      "doubanId": "1828115",
      "tmdbId": 4588,
      "imdbId": "",
      "title": "色，戒",
      "originalTitle": "",
      "year": "2007",
      "doubanRating": "8.7"
    },
    {
      "doubanRank": 136,
      "doubanId": "1291875",
      "tmdbId": 161285,
      "imdbId": "",
      "title": "阳光灿烂的日子",
      "originalTitle": "",
      "year": "1994",
      "doubanRating": "8.8"
    },
    {
      "doubanRank": 137,
      "doubanId": "1291579",
      "tmdbId": 585,
      "imdbId": "",
      "title": "怪兽电力公司",
      "originalTitle": "Monsters, Inc.",
      "year": "2001",
      "doubanRating": "8.8"
    },
    {
      "doubanRank": 138,
      "doubanId": "25814705",
      "tmdbId": 294682,
      "imdbId": "",
      "title": "小森林 夏秋篇",
      "originalTitle": "リトル・フォレスト 夏・秋",
      "year": "2014",
      "doubanRating": "9.0"
    },
    {
      "doubanRank": 139,
      "doubanId": "1294240",
      "tmdbId": 242,
      "imdbId": "",
      "title": "教父3",
      "originalTitle": "The Godfather: Part III",
      "year": "1990",
      "doubanRating": "9.0"
    },
    {
      "doubanRank": 140,
      "doubanId": "1292215",
      "tmdbId": 194,
      "imdbId": "",
      "title": "天使爱美丽",
      "originalTitle": "Le Fabuleux destin d'Amélie Poulain",
      "year": "2001",
      "doubanRating": "8.7"
    },
    {
      "doubanRank": 141,
      "doubanId": "1297052",
      "tmdbId": 37797,
      "imdbId": "",
      "title": "侧耳倾听",
      "originalTitle": "耳をすませば",
      "year": "1995",
      "doubanRating": "8.9"
    },
    {
      "doubanRank": 142,
      "doubanId": "1307315",
      "tmdbId": 74037,
      "imdbId": "",
      "title": "哪吒闹海",
      "originalTitle": "",
      "year": "1979",
      "doubanRating": "9.2"
    },
    {
      "doubanRank": 143,
      "doubanId": "1297518",
      "tmdbId": 55156,
      "imdbId": "",
      "title": "九品芝麻官",
      "originalTitle": "",
      "year": "1994",
      "doubanRating": "8.8"
    },
    {
      "doubanRank": 144,
      "doubanId": "6307447",
      "tmdbId": 68718,
      "imdbId": "",
      "title": "被解救的姜戈",
      "originalTitle": "Django Unchained",
      "year": "2012",
      "doubanRating": "8.8"
    },
    {
      "doubanRank": 145,
      "doubanId": "26799731",
      "tmdbId": 398818,
      "imdbId": "",
      "title": "请以你的名字呼唤我",
      "originalTitle": "Call Me by Your Name",
      "year": "2017",
      "doubanRating": "8.8"
    },
    {
      "doubanRank": 146,
      "doubanId": "1292274",
      "tmdbId": 594,
      "imdbId": "",
      "title": "幸福终点站",
      "originalTitle": "The Terminal",
      "year": "2004",
      "doubanRating": "8.8"
    },
    {
      "doubanRank": 147,
      "doubanId": "25986180",
      "tmdbId": 396535,
      "imdbId": "",
      "title": "釜山行",
      "originalTitle": "부산행",
      "year": "2016",
      "doubanRating": "8.6"
    },
    {
      "doubanRank": 148,
      "doubanId": "3287562",
      "tmdbId": 20352,
      "imdbId": "",
      "title": "神偷奶爸",
      "originalTitle": "Despicable Me",
      "year": "2010",
      "doubanRating": "8.7"
    },
    {
      "doubanRank": 149,
      "doubanId": "25814707",
      "tmdbId": 336026,
      "imdbId": "",
      "title": "小森林 冬春篇",
      "originalTitle": "リトル・フォレスト 冬・春",
      "year": "2015",
      "doubanRating": "9.0"
    },
    {
      "doubanRank": 150,
      "doubanId": "1303037",
      "tmdbId": 9261,
      "imdbId": "",
      "title": "喜宴",
      "originalTitle": "囍宴",
      "year": "1993",
      "doubanRating": "9.0"
    },
    {
      "doubanRank": 151,
      "doubanId": "5989818",
      "tmdbId": 92321,
      "imdbId": "",
      "title": "萤火之森",
      "originalTitle": "蛍火の杜へ",
      "year": "2011",
      "doubanRating": "8.8"
    },
    {
      "doubanRank": 152,
      "doubanId": "4268598",
      "tmdbId": 54186,
      "imdbId": "",
      "title": "告白",
      "originalTitle": "",
      "year": "2010",
      "doubanRating": "8.8"
    },
    {
      "doubanRank": 153,
      "doubanId": "3072124",
      "tmdbId": 24238,
      "imdbId": "",
      "title": "玛丽和麦克斯",
      "originalTitle": "Mary and Max",
      "year": "2009",
      "doubanRating": "9.0"
    },
    {
      "doubanRank": 154,
      "doubanId": "1295399",
      "tmdbId": 346,
      "imdbId": "",
      "title": "七武士",
      "originalTitle": "七人の侍",
      "year": "1954",
      "doubanRating": "9.3"
    },
    {
      "doubanRank": 155,
      "doubanId": "4920389",
      "tmdbId": 333339,
      "imdbId": "",
      "title": "头号玩家",
      "originalTitle": "Ready Player One",
      "year": "2018",
      "doubanRating": "8.6"
    },
    {
      "doubanRank": 156,
      "doubanId": "10463953",
      "tmdbId": 205596,
      "imdbId": "",
      "title": "模仿游戏",
      "originalTitle": "The Imitation Game",
      "year": "2014",
      "doubanRating": "8.8"
    },
    {
      "doubanRank": 157,
      "doubanId": "1293181",
      "tmdbId": 539,
      "imdbId": "",
      "title": "惊魂记",
      "originalTitle": "Psycho",
      "year": "1960",
      "doubanRating": "9.0"
    },
    {
      "doubanRank": 158,
      "doubanId": "1291545",
      "tmdbId": 587,
      "imdbId": "",
      "title": "大鱼",
      "originalTitle": "Big Fish",
      "year": "2003",
      "doubanRating": "8.8"
    },
    {
      "doubanRank": 159,
      "doubanId": "24733428",
      "tmdbId": 508442,
      "imdbId": "",
      "title": "心灵奇旅",
      "originalTitle": "Soul",
      "year": "2020",
      "doubanRating": "8.7"
    },
    {
      "doubanRank": 160,
      "doubanId": "35426925",
      "tmdbId": 838240,
      "imdbId": "",
      "title": "机器人之梦",
      "originalTitle": "Robot Dreams",
      "year": "2023",
      "doubanRating": "9.1"
    },
    {
      "doubanRank": 161,
      "doubanId": "1307856",
      "tmdbId": 295279,
      "imdbId": "",
      "title": "背靠背，脸对脸",
      "originalTitle": "",
      "year": "1994",
      "doubanRating": "9.5"
    },
    {
      "doubanRank": 162,
      "doubanId": "1316510",
      "tmdbId": 55157,
      "imdbId": "",
      "title": "射雕英雄传之东成西就",
      "originalTitle": "射鵰英雄傳之東成西就",
      "year": "1993",
      "doubanRating": "8.7"
    },
    {
      "doubanRank": 163,
      "doubanId": "26325320",
      "tmdbId": 324786,
      "imdbId": "",
      "title": "血战钢锯岭",
      "originalTitle": "Hacksaw Ridge",
      "year": "2016",
      "doubanRating": "8.7"
    },
    {
      "doubanRank": 164,
      "doubanId": "26683290",
      "tmdbId": 372058,
      "imdbId": "",
      "title": "你的名字。",
      "originalTitle": "君の名は。",
      "year": "2016",
      "doubanRating": "8.5"
    },
    {
      "doubanRank": 165,
      "doubanId": "1306861",
      "tmdbId": 10950,
      "imdbId": "",
      "title": "我是山姆",
      "originalTitle": "I Am Sam",
      "year": "2001",
      "doubanRating": "9.0"
    },
    {
      "doubanRank": 166,
      "doubanId": "4917726",
      "tmdbId": 77117,
      "imdbId": "",
      "title": "阳光姐妹淘",
      "originalTitle": "써니",
      "year": "2011",
      "doubanRating": "8.8"
    },
    {
      "doubanRank": 167,
      "doubanId": "21360417",
      "tmdbId": 209764,
      "imdbId": "",
      "title": "恐怖直播",
      "originalTitle": "더 테러 라이브",
      "year": "2013",
      "doubanRating": "8.7"
    },
    {
      "doubanRank": 168,
      "doubanId": "1302467",
      "tmdbId": 605,
      "imdbId": "",
      "title": "黑客帝国3：矩阵革命",
      "originalTitle": "The Matrix Revolutions",
      "year": "2003",
      "doubanRating": "8.8"
    },
    {
      "doubanRank": 169,
      "doubanId": "1291992",
      "tmdbId": 1541,
      "imdbId": "",
      "title": "末路狂花",
      "originalTitle": "Thelma & Louise",
      "year": "1991",
      "doubanRating": "9.0"
    },
    {
      "doubanRank": 170,
      "doubanId": "27119724",
      "tmdbId": 475557,
      "imdbId": "",
      "title": "小丑",
      "originalTitle": "Joker",
      "year": "2019",
      "doubanRating": "8.7"
    },
    {
      "doubanRank": 171,
      "doubanId": "26611804",
      "tmdbId": 359940,
      "imdbId": "",
      "title": "三块广告牌",
      "originalTitle": "Three Billboards Outside Ebbing, Missouri",
      "year": "2017",
      "doubanRating": "8.7"
    },
    {
      "doubanRank": 172,
      "doubanId": "1578507",
      "tmdbId": 2503,
      "imdbId": "",
      "title": "谍影重重3",
      "originalTitle": "The Bourne Ultimatum",
      "year": "2007",
      "doubanRating": "8.9"
    },
    {
      "doubanRank": 173,
      "doubanId": "1422283",
      "tmdbId": 258424,
      "imdbId": "",
      "title": "高山下的花环",
      "originalTitle": "",
      "year": "1984(中国大陆)",
      "doubanRating": "9.5"
    },
    {
      "doubanRank": 174,
      "doubanId": "1417598",
      "tmdbId": 176,
      "imdbId": "",
      "title": "电锯惊魂",
      "originalTitle": "Saw",
      "year": "2004",
      "doubanRating": "8.7"
    },
    {
      "doubanRank": 175,
      "doubanId": "1307106",
      "tmdbId": 11647,
      "imdbId": "",
      "title": "无间道2",
      "originalTitle": "無間道II",
      "year": "2003",
      "doubanRating": "8.8"
    },
    {
      "doubanRank": 176,
      "doubanId": "1793929",
      "tmdbId": 152532,
      "imdbId": "",
      "title": "达拉斯买家俱乐部",
      "originalTitle": "Dallas Buyers Club",
      "year": "2013",
      "doubanRating": "8.8"
    },
    {
      "doubanRank": 177,
      "doubanId": "1907966",
      "tmdbId": 49519,
      "imdbId": "",
      "title": "疯狂原始人",
      "originalTitle": "The Croods",
      "year": "2013",
      "doubanRating": "8.7"
    },
    {
      "doubanRank": 178,
      "doubanId": "1300374",
      "tmdbId": 497,
      "imdbId": "",
      "title": "绿里奇迹",
      "originalTitle": "The Green Mile",
      "year": "1999",
      "doubanRating": "8.9"
    },
    {
      "doubanRank": 179,
      "doubanId": "10808442",
      "tmdbId": 132344,
      "imdbId": "",
      "title": "爱在午夜降临前",
      "originalTitle": "Before Midnight",
      "year": "2013",
      "doubanRating": "8.9"
    },
    {
      "doubanRank": 180,
      "doubanId": "1862151",
      "tmdbId": 45380,
      "imdbId": "",
      "title": "疯狂的石头",
      "originalTitle": "",
      "year": "2006",
      "doubanRating": "8.6"
    },
    {
      "doubanRank": 181,
      "doubanId": "1293460",
      "tmdbId": 872,
      "imdbId": "",
      "title": "雨中曲",
      "originalTitle": "Singin' in the Rain",
      "year": "1952",
      "doubanRating": "9.1"
    },
    {
      "doubanRank": 182,
      "doubanId": "1292226",
      "tmdbId": 62,
      "imdbId": "",
      "title": "2001太空漫游",
      "originalTitle": "2001: A Space Odyssey",
      "year": "1968",
      "doubanRating": "8.9"
    },
    {
      "doubanRank": 183,
      "doubanId": "25895901",
      "tmdbId": 315846,
      "imdbId": "",
      "title": "海街日记",
      "originalTitle": "海街diary",
      "year": "2015",
      "doubanRating": "8.8"
    },
    {
      "doubanRank": 184,
      "doubanId": "1291585",
      "tmdbId": 81,
      "imdbId": "",
      "title": "风之谷",
      "originalTitle": "風の谷のナウシカ",
      "year": "1984",
      "doubanRating": "8.9"
    },
    {
      "doubanRank": 185,
      "doubanId": "1292208",
      "tmdbId": 598,
      "imdbId": "",
      "title": "上帝之城",
      "originalTitle": "Cidade de Deus",
      "year": "2002",
      "doubanRating": "9.0"
    },
    {
      "doubanRank": 186,
      "doubanId": "25917973",
      "tmdbId": 292362,
      "imdbId": "",
      "title": "心迷宫",
      "originalTitle": "",
      "year": "2014",
      "doubanRating": "8.7"
    },
    {
      "doubanRank": 187,
      "doubanId": "1297574",
      "tmdbId": 11471,
      "imdbId": "",
      "title": "英雄本色",
      "originalTitle": "",
      "year": "1986",
      "doubanRating": "8.6"
    },
    {
      "doubanRank": 188,
      "doubanId": "1304447",
      "tmdbId": 77,
      "imdbId": "",
      "title": "记忆碎片",
      "originalTitle": "Memento",
      "year": "2000",
      "doubanRating": "8.7"
    },
    {
      "doubanRank": 189,
      "doubanId": "1295409",
      "tmdbId": 47423,
      "imdbId": "",
      "title": "纵横四海",
      "originalTitle": "縱橫四海",
      "year": "1991",
      "doubanRating": "8.8"
    },
    {
      "doubanRank": 190,
      "doubanId": "6534248",
      "tmdbId": 82690,
      "imdbId": "",
      "title": "无敌破坏王",
      "originalTitle": "Wreck-It Ralph",
      "year": "2012",
      "doubanRating": "8.7"
    },
    {
      "doubanRank": 191,
      "doubanId": "1291822",
      "tmdbId": 205,
      "imdbId": "",
      "title": "卢旺达饭店",
      "originalTitle": "Hotel Rwanda",
      "year": "2004",
      "doubanRating": "8.9"
    },
    {
      "doubanRank": 192,
      "doubanId": "1310177",
      "tmdbId": 13398,
      "imdbId": "",
      "title": "东京教父",
      "originalTitle": "東京ゴッドファーザーズ",
      "year": "2003",
      "doubanRating": "9.0"
    },
    {
      "doubanRank": 193,
      "doubanId": "1292329",
      "tmdbId": 15804,
      "imdbId": "",
      "title": "牯岭街少年杀人事件",
      "originalTitle": "牯嶺街少年殺人事件",
      "year": "1991",
      "doubanRating": "8.9"
    },
    {
      "doubanRank": 194,
      "doubanId": "3011051",
      "tmdbId": 26466,
      "imdbId": "",
      "title": "恐怖游轮",
      "originalTitle": "Triangle",
      "year": "2009",
      "doubanRating": "8.5"
    },
    {
      "doubanRank": 195,
      "doubanId": "27622447",
      "tmdbId": 505192,
      "imdbId": "",
      "title": "小偷家族",
      "originalTitle": "万引き家族",
      "year": "2018",
      "doubanRating": "8.7"
    },
    {
      "doubanRank": 196,
      "doubanId": "1307811",
      "tmdbId": 16859,
      "imdbId": "",
      "title": "魔女宅急便",
      "originalTitle": "魔女の宅急便",
      "year": "1989",
      "doubanRating": "8.7"
    },
    {
      "doubanRank": 197,
      "doubanId": "1291578",
      "tmdbId": 425,
      "imdbId": "",
      "title": "冰川时代",
      "originalTitle": "Ice Age",
      "year": "2002",
      "doubanRating": "8.7"
    },
    {
      "doubanRank": 198,
      "doubanId": "1297880",
      "tmdbId": 122973,
      "imdbId": "",
      "title": "芙蓉镇",
      "originalTitle": "",
      "year": "1987",
      "doubanRating": "9.3"
    },
    {
      "doubanRank": 199,
      "doubanId": "1959195",
      "tmdbId": 31743,
      "imdbId": "",
      "title": "忠犬八公物语",
      "originalTitle": "ハチ公物語",
      "year": "1987",
      "doubanRating": "9.2"
    },
    {
      "doubanRank": 200,
      "doubanId": "3792799",
      "tmdbId": 39693,
      "imdbId": "",
      "title": "岁月神偷",
      "originalTitle": "歲月神偷",
      "year": "2010",
      "doubanRating": "8.7"
    },
    {
      "doubanRank": 201,
      "doubanId": "1867345",
      "tmdbId": 7350,
      "imdbId": "",
      "title": "遗愿清单",
      "originalTitle": "The Bucket List",
      "year": "2007",
      "doubanRating": "8.7"
    },
    {
      "doubanRank": 202,
      "doubanId": "24750126",
      "tmdbId": 265195,
      "imdbId": "",
      "title": "荒蛮故事",
      "originalTitle": "Relatos salvajes",
      "year": "2014",
      "doubanRating": "8.7"
    },
    {
      "doubanRank": 203,
      "doubanId": "27059130",
      "tmdbId": 475149,
      "imdbId": "",
      "title": "大佛普拉斯",
      "originalTitle": "",
      "year": "2017",
      "doubanRating": "8.7"
    },
    {
      "doubanRank": 204,
      "doubanId": "3075287",
      "tmdbId": 45612,
      "imdbId": "",
      "title": "源代码",
      "originalTitle": "Source Code",
      "year": "2011",
      "doubanRating": "8.6"
    },
    {
      "doubanRank": 205,
      "doubanId": "34874432",
      "tmdbId": 695932,
      "imdbId": "",
      "title": "花束般的恋爱",
      "originalTitle": "花束みたいな恋をした",
      "year": "2021",
      "doubanRating": "8.6"
    },
    {
      "doubanRank": 206,
      "doubanId": "2133323",
      "tmdbId": 116745,
      "imdbId": "",
      "title": "白日梦想家",
      "originalTitle": "The Secret Life of Walter Mitty",
      "year": "2013",
      "doubanRating": "8.6"
    },
    {
      "doubanRank": 207,
      "doubanId": "25934014",
      "tmdbId": 313369,
      "imdbId": "",
      "title": "爱乐之城",
      "originalTitle": "La La Land",
      "year": "2016",
      "doubanRating": "8.4"
    },
    {
      "doubanRank": 208,
      "doubanId": "3592854",
      "tmdbId": 76341,
      "imdbId": "",
      "title": "疯狂的麦克斯4：狂暴之路",
      "originalTitle": "Mad Max: Fury Road",
      "year": "2015",
      "doubanRating": "8.7"
    },
    {
      "doubanRank": 209,
      "doubanId": "1308857",
      "tmdbId": 16074,
      "imdbId": "",
      "title": "可可西里",
      "originalTitle": "",
      "year": "2004",
      "doubanRating": "8.9"
    },
    {
      "doubanRank": 210,
      "doubanId": "4848115",
      "tmdbId": 89825,
      "imdbId": "",
      "title": "你看起来好像很好吃",
      "originalTitle": "おまえうまそうだな",
      "year": "2010",
      "doubanRating": "8.9"
    },
    {
      "doubanRank": 211,
      "doubanId": "2209573",
      "tmdbId": 12405,
      "imdbId": "",
      "title": "贫民窟的百万富翁",
      "originalTitle": "Slumdog Millionaire",
      "year": "2008",
      "doubanRating": "8.6"
    },
    {
      "doubanRank": 212,
      "doubanId": "5300054",
      "tmdbId": 424694,
      "imdbId": "",
      "title": "波西米亚狂想曲",
      "originalTitle": "Bohemian Rhapsody",
      "year": "2018",
      "doubanRating": "8.6"
    },
    {
      "doubanRank": 213,
      "doubanId": "1293908",
      "tmdbId": 901,
      "imdbId": "",
      "title": "城市之光",
      "originalTitle": "City Lights",
      "year": "1931",
      "doubanRating": "9.3"
    },
    {
      "doubanRank": 214,
      "doubanId": "25773932",
      "tmdbId": 244786,
      "imdbId": "",
      "title": "爆裂鼓手",
      "originalTitle": "Whiplash",
      "year": "2014",
      "doubanRating": "8.6"
    },
    {
      "doubanRank": 215,
      "doubanId": "1303394",
      "tmdbId": 39915,
      "imdbId": "",
      "title": "青蛇",
      "originalTitle": "",
      "year": "1993",
      "doubanRating": "8.6"
    },
    {
      "doubanRank": 216,
      "doubanId": "1292328",
      "tmdbId": 40751,
      "imdbId": "",
      "title": "东邪西毒",
      "originalTitle": "東邪西毒",
      "year": "1994",
      "doubanRating": "8.6"
    },
    {
      "doubanRank": 217,
      "doubanId": "2051007",
      "tmdbId": 12444,
      "imdbId": "",
      "title": "哈利·波特与死亡圣器(上)",
      "originalTitle": "Harry Potter and the Deathly Hallows: Part 1",
      "year": "2010",
      "doubanRating": "8.6"
    },
    {
      "doubanRank": 218,
      "doubanId": "1438652",
      "tmdbId": 16869,
      "imdbId": "",
      "title": "无耻混蛋",
      "originalTitle": "Inglourious Basterds",
      "year": "2009",
      "doubanRating": "8.7"
    },
    {
      "doubanRank": 219,
      "doubanId": "1291844",
      "tmdbId": 280,
      "imdbId": "",
      "title": "终结者2：审判日",
      "originalTitle": "Terminator 2: Judgment Day",
      "year": "1991",
      "doubanRating": "8.8"
    },
    {
      "doubanRank": 220,
      "doubanId": "1293323",
      "tmdbId": 10404,
      "imdbId": "",
      "title": "大红灯笼高高挂",
      "originalTitle": "",
      "year": "1991",
      "doubanRating": "8.8"
    },
    {
      "doubanRank": 221,
      "doubanId": "1978709",
      "tmdbId": 44214,
      "imdbId": "",
      "title": "黑天鹅",
      "originalTitle": "Black Swan",
      "year": "2010",
      "doubanRating": "8.6"
    },
    {
      "doubanRank": 222,
      "doubanId": "1292287",
      "tmdbId": 40213,
      "imdbId": "",
      "title": "新龙门客栈",
      "originalTitle": "新龍門客棧",
      "year": "1992",
      "doubanRating": "8.7"
    },
    {
      "doubanRank": 223,
      "doubanId": "4739952",
      "tmdbId": 57627,
      "imdbId": "",
      "title": "初恋这件小事",
      "originalTitle": "สิ่งเล็กเล็กที่เรียกว่า...รัก",
      "year": "2010",
      "doubanRating": "8.5"
    },
    {
      "doubanRank": 224,
      "doubanId": "1300117",
      "tmdbId": 782,
      "imdbId": "",
      "title": "千钧一发",
      "originalTitle": "Gattaca",
      "year": "1997",
      "doubanRating": "8.8"
    },
    {
      "doubanRank": 225,
      "doubanId": "1302827",
      "tmdbId": 644,
      "imdbId": "",
      "title": "人工智能",
      "originalTitle": "A.I. Artificial Intelligence",
      "year": "2001",
      "doubanRating": "8.7"
    },
    {
      "doubanRank": 226,
      "doubanId": "1959877",
      "tmdbId": 12429,
      "imdbId": "",
      "title": "崖上的波妞",
      "originalTitle": "崖の上のポニョ",
      "year": "2008",
      "doubanRating": "8.6"
    },
    {
      "doubanRank": 227,
      "doubanId": "1291870",
      "tmdbId": 380,
      "imdbId": "",
      "title": "雨人",
      "originalTitle": "Rain Man",
      "year": "1988",
      "doubanRating": "8.7"
    },
    {
      "doubanRank": 228,
      "doubanId": "1296909",
      "tmdbId": 8290,
      "imdbId": "",
      "title": "虎口脱险",
      "originalTitle": "La grande vadrouille",
      "year": "1966",
      "doubanRating": "8.9"
    },
    {
      "doubanRank": 229,
      "doubanId": "1457217",
      "tmdbId": 675,
      "imdbId": "",
      "title": "哈利·波特与凤凰社",
      "originalTitle": "Harry Potter and the Order of the Phoenix",
      "year": "2007",
      "doubanRating": "8.6"
    },
    {
      "doubanRank": 230,
      "doubanId": "25807345",
      "tmdbId": 220289,
      "imdbId": "",
      "title": "彗星来的那一夜",
      "originalTitle": "Coherence",
      "year": "2013",
      "doubanRating": "8.6"
    },
    {
      "doubanRank": 231,
      "doubanId": "1291879",
      "tmdbId": 548,
      "imdbId": "",
      "title": "罗生门",
      "originalTitle": "羅生門",
      "year": "1950",
      "doubanRating": "8.8"
    },
    {
      "doubanRank": 232,
      "doubanId": "25980443",
      "tmdbId": 334541,
      "imdbId": "",
      "title": "海边的曼彻斯特",
      "originalTitle": "Manchester by the Sea",
      "year": "2016",
      "doubanRating": "8.6"
    },
    {
      "doubanRank": 233,
      "doubanId": "1309163",
      "tmdbId": 11036,
      "imdbId": "",
      "title": "恋恋笔记本",
      "originalTitle": "The Notebook",
      "year": "2004",
      "doubanRating": "8.5"
    },
    {
      "doubanRank": 234,
      "doubanId": "25864085",
      "tmdbId": 286217,
      "imdbId": "",
      "title": "火星救援",
      "originalTitle": "The Martian",
      "year": "2015",
      "doubanRating": "8.5"
    },
    {
      "doubanRank": 235,
      "doubanId": "1292401",
      "tmdbId": 508,
      "imdbId": "",
      "title": "真爱至上",
      "originalTitle": "Love Actually",
      "year": "2003",
      "doubanRating": "8.5"
    },
    {
      "doubanRank": 236,
      "doubanId": "1304141",
      "tmdbId": 604,
      "imdbId": "",
      "title": "黑客帝国2：重装上阵",
      "originalTitle": "The Matrix Reloaded",
      "year": "2003",
      "doubanRating": "8.7"
    },
    {
      "doubanRank": 237,
      "doubanId": "4202982",
      "tmdbId": 109445,
      "imdbId": "",
      "title": "冰雪奇缘",
      "originalTitle": "Frozen",
      "year": "2013",
      "doubanRating": "8.5"
    },
    {
      "doubanRank": 238,
      "doubanId": "2222996",
      "tmdbId": 25050,
      "imdbId": "",
      "title": "步履不停",
      "originalTitle": "歩いても 歩いても",
      "year": "2008",
      "doubanRating": "8.8"
    },
    {
      "doubanRank": 239,
      "doubanId": "26787574",
      "tmdbId": 406997,
      "imdbId": "",
      "title": "奇迹男孩",
      "originalTitle": "Wonder",
      "year": "2017",
      "doubanRating": "8.6"
    },
    {
      "doubanRank": 240,
      "doubanId": "1307394",
      "tmdbId": 33320,
      "imdbId": "",
      "title": "千年女优",
      "originalTitle": "千年女優",
      "year": "2001",
      "doubanRating": "8.8"
    },
    {
      "doubanRank": 241,
      "doubanId": "1419936",
      "tmdbId": 1830,
      "imdbId": "",
      "title": "战争之王",
      "originalTitle": "Lord of War",
      "year": "2005",
      "doubanRating": "8.7"
    },
    {
      "doubanRank": 242,
      "doubanId": "1308767",
      "tmdbId": 2502,
      "imdbId": "",
      "title": "谍影重重2",
      "originalTitle": "The Bourne Supremacy",
      "year": "2004",
      "doubanRating": "8.7"
    },
    {
      "doubanRank": 243,
      "doubanId": "26374197",
      "tmdbId": 324857,
      "imdbId": "",
      "title": "蜘蛛侠：平行宇宙",
      "originalTitle": "Spider-Man: Into the Spider-Verse",
      "year": "2018",
      "doubanRating": "8.6"
    },
    {
      "doubanRank": 244,
      "doubanId": "1291936",
      "tmdbId": 9323,
      "imdbId": "",
      "title": "攻壳机动队",
      "originalTitle": "攻殻機動隊",
      "year": "1995",
      "doubanRating": "9.0"
    },
    {
      "doubanRank": 245,
      "doubanId": "1428175",
      "tmdbId": 1372,
      "imdbId": "",
      "title": "血钻",
      "originalTitle": "Blood Diamond",
      "year": "2006",
      "doubanRating": "8.7"
    },
    {
      "doubanRank": 246,
      "doubanId": "25977027",
      "tmdbId": 290098,
      "imdbId": "",
      "title": "小姐",
      "originalTitle": "아가씨",
      "year": "2016",
      "doubanRating": "8.5"
    },
    {
      "doubanRank": 247,
      "doubanId": "26615208",
      "tmdbId": 381284,
      "imdbId": "",
      "title": "隐藏人物",
      "originalTitle": "Hidden Figures",
      "year": "2016",
      "doubanRating": "8.9"
    },
    {
      "doubanRank": 248,
      "doubanId": "27113517",
      "tmdbId": 478804,
      "imdbId": "",
      "title": "血观音",
      "originalTitle": "血觀音",
      "year": "2017",
      "doubanRating": "8.6"
    },
    {
      "doubanRank": 249,
      "doubanId": "1293964",
      "tmdbId": 43824,
      "imdbId": "",
      "title": "魂断蓝桥",
      "originalTitle": "Waterloo Bridge",
      "year": "1940",
      "doubanRating": "8.8"
    },
    {
      "doubanRank": 250,
      "doubanId": "25724855",
      "tmdbId": 264644,
      "imdbId": "",
      "title": "房间",
      "originalTitle": "Room",
      "year": "2015",
      "doubanRating": "8.7"
    }
  ]
}